monty_hall_game/__init__.py
monty_hall_game/game_exceptions.py
monty_hall_game/monty_hall_game.py
monty_hall_game/templates/final.html
monty_hall_game/templates/layout7.html
monty_hall_game/templates/reselect.html
monty_hall_game/templates/select.html
uio_monty_hall_game-2020.11.1.data/scripts/play_monty_hall_cli.py
uio_monty_hall_game-2020.11.1.data/scripts/play_monty_hall_web.py
uio_monty_hall_game-2020.11.1.dist-info/METADATA
uio_monty_hall_game-2020.11.1.dist-info/WHEEL
uio_monty_hall_game-2020.11.1.dist-info/top_level.txt
uio_monty_hall_game-2020.11.1.dist-info/RECORD
