Metadata-Version: 2.1
Name: uio-monty-hall-game
Version: 2020.11.1
Summary: A game implementation of the Monty Hall problem.
Home-page: UNKNOWN
Author: Simon Funke
Author-email: simon@simula.no
License: BSD
Platform: UNKNOWN
Requires-Dist: flask
Requires-Dist: gunicorn
